soco_parser/__init__.py
soco_parser/cloud.py
soco_parser/config.py
soco_parser/doc_api.py
soco_parser/utils.py
soco_doc_parser_python-0.0.1.dist-info/LICENSE
soco_doc_parser_python-0.0.1.dist-info/METADATA
soco_doc_parser_python-0.0.1.dist-info/WHEEL
soco_doc_parser_python-0.0.1.dist-info/top_level.txt
soco_doc_parser_python-0.0.1.dist-info/RECORD
