Metadata-Version: 2.1
Name: soco-doc-parser-python
Version: 0.0.1
Summary: Python SDK for using SOCO platform
Home-page: https://www.soco.ai
Author: kyusonglee
License: UNKNOWN
Platform: UNKNOWN
Classifier: Programming Language :: Python :: 3
Classifier: License :: Free for non-commercial use
Classifier: Operating System :: OS Independent
Requires-Dist: unoconv (>=0.9.0)
Requires-Dist: boto3 (>=1.10.16)
